my_package/__init__.py
my_package/main.py
my_package_cubcloud5-0.1.0.dist-info/LICENSE
my_package_cubcloud5-0.1.0.dist-info/METADATA
my_package_cubcloud5-0.1.0.dist-info/WHEEL
my_package_cubcloud5-0.1.0.dist-info/top_level.txt
my_package_cubcloud5-0.1.0.dist-info/RECORD
