Metadata-Version: 2.1
Name: my_package_cubcloud5
Version: 0.1.0
Summary: คำอธิบาย package ของคุณ
Author-email: ชื่อคุณ <email@example.com>
Requires-Python: >=3.7
License-File: LICENSE
